subtitles2text/main.py
subtitles2text-0.0.3.dist-info/LICENSE
subtitles2text-0.0.3.dist-info/METADATA
subtitles2text-0.0.3.dist-info/WHEEL
subtitles2text-0.0.3.dist-info/entry_points.txt
subtitles2text-0.0.3.dist-info/top_level.txt
subtitles2text-0.0.3.dist-info/RECORD
